Metadata-Version: 2.1
Name: lighter-v2-python
Version: 1.0.0
Summary: lighter Python rest api and blockchain interactions for Limit Orders
Home-page: https://github.com/elliottech/lighter-v2-python
Author: Elliot
Author-email: ahmet@elliot.ai
License: Apache 2.0
Keywords: lighter exchange rest api defi ethereum optimism l2 eth
Classifier: Intended Audience :: Developers
Classifier: License :: OSI Approved :: Apache Software License
Classifier: Operating System :: OS Independent
Classifier: Programming Language :: Python :: 3.9
Classifier: Programming Language :: Python :: 3.10
Classifier: Programming Language :: Python :: 3.11
Classifier: Programming Language :: Python
Classifier: Topic :: Software Development :: Libraries :: Python Modules
License-File: LICENSE
Requires-Dist: eth-account >=0.4.0
Requires-Dist: pytest >=7.2.2
Requires-Dist: pytest-mock >=3.0.0
Requires-Dist: requests-mock >=1.6.0
Requires-Dist: requests >=2.22.0
Requires-Dist: setuptools >=50.3.2
Requires-Dist: tox ==3.25.0
Requires-Dist: web3 >=6.0.0
Requires-Dist: dateparser >=1.0.0
Requires-Dist: nest-asyncio >=1.5.6
Requires-Dist: pytest-asyncio >=0.21.0
